tf_jieba/__init__.py
tf_jieba/jieba_op.py
tf_jieba/jieba_op_test.py
tf_jieba/x_ops.cpython-36m-darwin.so
tf_jieba/cppjieba_dict/hmm_model.utf8
tf_jieba/cppjieba_dict/idf.utf8
tf_jieba/cppjieba_dict/jieba.dict.utf8
tf_jieba/cppjieba_dict/stop_words.utf8
tf_jieba/cppjieba_dict/user.dict.utf8
tf_jieba-0.3.dist-info/METADATA
tf_jieba-0.3.dist-info/WHEEL
tf_jieba-0.3.dist-info/top_level.txt
tf_jieba-0.3.dist-info/RECORD
