Metadata-Version: 2.1
Name: tf-jieba
Version: 0.3
Summary: Tensorflow Operation Wrapper of cppjieba (Chinese Word Segamentation)
Home-page: https://github.com/applenob/tf_jieba
Author: Javen Chen
Author-email: applecer@pku.edu.cn
Maintainer: Javen Chen
Maintainer-email: applecer@pku.edu.cn
License: UNKNOWN
Download-URL: https://github.com/applenob/tf_jieba/tarball/2019-10-21
Platform: Windows
Platform: MacOS
Platform: Unix
Classifier: Development Status :: 4 - Beta
Classifier: Intended Audience :: Education
Classifier: License :: OSI Approved :: MIT License
Classifier: Natural Language :: English
Classifier: Operating System :: MacOS
Classifier: Operating System :: POSIX :: Linux
Classifier: Programming Language :: Python :: 3.6
